examples/README.md
examples/advanced_usage.py
examples/basic_usage.py
examples/extended_detection.py
maskinfo/__init__.py
maskinfo/__main__.py
maskinfo/change_displayer.py
maskinfo/cli.py
maskinfo/detector.py
maskinfo/file_handler.py
maskinfo/masker.py
maskinfojp-0.1.2.dist-info/licenses/LICENSE
maskinfojp-0.1.2.dist-info/METADATA
maskinfojp-0.1.2.dist-info/WHEEL
maskinfojp-0.1.2.dist-info/entry_points.txt
maskinfojp-0.1.2.dist-info/top_level.txt
maskinfojp-0.1.2.dist-info/RECORD
