Metadata-Version: 2.4
Name: maskinfojp
Version: 0.1.2
Summary: A library to mask sensitive information in files and restore it back
Home-page: https://github.com/yourusername/maskinfo
Author: Your Name
Author-email: Hayashi Kunita <hayashi.kunita@example.com>
License: MIT
Project-URL: Homepage, https://github.com/hayashikunita/maskinfojp
Project-URL: Repository, https://github.com/hayashikunita/maskinfojp
Project-URL: Issues, https://github.com/hayashikunita/maskinfojp/issues
Keywords: security,privacy,masking,sensitive-data
Classifier: Development Status :: 4 - Beta
Classifier: Intended Audience :: Developers
Classifier: License :: OSI Approved :: MIT License
Classifier: Operating System :: OS Independent
Classifier: Programming Language :: Python :: 3
Classifier: Programming Language :: Python :: 3.8
Classifier: Programming Language :: Python :: 3.9
Classifier: Programming Language :: Python :: 3.10
Classifier: Programming Language :: Python :: 3.11
Classifier: Programming Language :: Python :: 3.12
Classifier: Topic :: Security
Classifier: Topic :: Software Development :: Libraries :: Python Modules
Classifier: Topic :: Text Processing
Requires-Python: >=3.7
License-File: LICENSE
Requires-Dist: click>=7.0
Requires-Dist: chardet>=3.0.4
Provides-Extra: dev
Requires-Dist: pytest>=6.0; extra == "dev"
Requires-Dist: pytest-cov; extra == "dev"
Requires-Dist: black>=23.0.0; extra == "dev"
Requires-Dist: flake8>=7.0.0; extra == "dev"
Requires-Dist: flake8-docstrings; extra == "dev"
Requires-Dist: mypy>=1.0.0; extra == "dev"
Requires-Dist: isort>=5.12.0; extra == "dev"
Requires-Dist: pre-commit>=3.0.0; extra == "dev"
Requires-Dist: bandit>=1.7.0; extra == "dev"
Requires-Dist: pyupgrade>=3.0.0; extra == "dev"
Requires-Dist: types-chardet; extra == "dev"
Dynamic: author
Dynamic: home-page
Dynamic: license-file
Dynamic: requires-python
